rivabar/__init__.py
rivabar/analysis.py
rivabar/core.py
rivabar/data_io.py
rivabar/debug_script.py
rivabar/geometry_utils.py
rivabar/graph_processing.py
rivabar/interactive_graph_editor.py
rivabar/polygon_processing.py
rivabar/rivabar_legacy.py
rivabar/rivabar_straighten.py
rivabar/river.py
rivabar/temporal_analysis.py
rivabar/utils.py
rivabar/visualization.py
rivabar-0.1.2.dist-info/licenses/LICENSE
rivabar-0.1.2.dist-info/METADATA
rivabar-0.1.2.dist-info/WHEEL
rivabar-0.1.2.dist-info/top_level.txt
rivabar-0.1.2.dist-info/RECORD
