Metadata-Version: 2.4
Name: rivabar
Version: 0.1.2
Summary: A Python package to automatically extract channel centerlines and banklines from water index images of rivers
Home-page: https://github.com/zsylvester/rivabar
Author: Zoltan Sylvester
Author-email: zsylvester@gmail.com
Classifier: Programming Language :: Python :: 3
Classifier: License :: OSI Approved :: MIT License
Classifier: Operating System :: OS Independent
Classifier: Topic :: Scientific/Engineering :: GIS
Classifier: Topic :: Scientific/Engineering :: Image Processing
Requires-Python: >=3.10
License-File: LICENSE
Requires-Dist: numpy>=2.0.0
Requires-Dist: matplotlib>=3.9.0
Requires-Dist: pandas>=2.2.0
Requires-Dist: scipy>=1.14.0
Requires-Dist: scikit-image>=0.24.0
Requires-Dist: opencv-python>=4.10.0
Requires-Dist: sknw>=0.15
Requires-Dist: networkx>=3.4.0
Requires-Dist: scikit-learn>=1.5.0
Requires-Dist: rasterio>=1.4.0
Requires-Dist: shapely>=2.0.0
Requires-Dist: libpysal>=4.12.0
Requires-Dist: geopandas>=1.0.0
Requires-Dist: momepy>=0.9.0
Requires-Dist: tqdm>=4.67.0
Dynamic: author
Dynamic: author-email
Dynamic: classifier
Dynamic: description
Dynamic: description-content-type
Dynamic: home-page
Dynamic: license-file
Dynamic: requires-dist
Dynamic: requires-python
Dynamic: summary
